mdtree/__init__.py
mdtree/__main__.py
mdtree/test/test_cli.py
mdtree/test/test_gitignore.py
mdtree/test/test_gitignore_comprehensive.py
mdtree/test/test_gitignore_dir_rules.py
mdtree/test/test_gitignore_glob_dir.py
mdtree/test/test_structure.py
mdtree/treebuilder.py
mdtree_py-0.1.8.dist-info/LICENSE
mdtree_py-0.1.8.dist-info/METADATA
mdtree_py-0.1.8.dist-info/WHEEL
mdtree_py-0.1.8.dist-info/entry_points.txt
mdtree_py-0.1.8.dist-info/RECORD
