Metadata-Version: 2.3
Name: mdtree-py
Version: 0.1.8
Summary: Output directory structure as Markdown code block
License: MIT
Author: a-duty-rookie
Author-email: yutaro1127@gmail.com
Requires-Python: >=3.9
Classifier: License :: OSI Approved :: MIT License
Classifier: Programming Language :: Python :: 3
Classifier: Programming Language :: Python :: 3.9
Classifier: Programming Language :: Python :: 3.10
Classifier: Programming Language :: Python :: 3.11
Classifier: Programming Language :: Python :: 3.12
Classifier: Programming Language :: Python :: 3.13
Requires-Dist: click (>=8.1.8)
Requires-Dist: pathspec (>=0.12.1)
Requires-Dist: pyperclip (>=1.9.0)
